go_ssh-0.2.0.dist-info/licenses/LICENSE
gossh/__init__.py
gossh/gossh.py
go_ssh-0.2.0.dist-info/METADATA
go_ssh-0.2.0.dist-info/WHEEL
go_ssh-0.2.0.dist-info/entry_points.txt
go_ssh-0.2.0.dist-info/top_level.txt
go_ssh-0.2.0.dist-info/RECORD
