Metadata-Version: 2.4
Name: go-ssh
Version: 0.2.0
Summary: Smart SSH connector using fuzzy host search and auto-key upload
Home-page: https://pypi.org/project/go-ssh/
Author: Mr kumar
Author-email: mrpirate404@gmail.com
Classifier: Programming Language :: Python :: 3
Classifier: Operating System :: OS Independent
Requires-Python: >=3.6
License-File: LICENSE
Requires-Dist: paramiko
Requires-Dist: keyring
Dynamic: author
Dynamic: author-email
Dynamic: classifier
Dynamic: description
Dynamic: description-content-type
Dynamic: home-page
Dynamic: license-file
Dynamic: requires-dist
Dynamic: requires-python
Dynamic: summary
